gsblmao/__init__.py
gsblmao/__main__.py
gsblmao/stick_bug.py
gsblmao/media/note0.wav
gsblmao/media/note1.wav
gsblmao/media/note2.wav
gsblmao/media/note3.wav
gsblmao/media/note4.wav
gsblmao/media/note5.wav
gsblmao/media/note6.wav
gsblmao/media/note7.wav
gsblmao/media/note8.wav
gsblmao/media/note9.wav
gsblmao/media/stick_bug.mp4
gsblmao/media/transform.wav
get_stick_bugged_lmao-1.0.2.dist-info/LICENSE
get_stick_bugged_lmao-1.0.2.dist-info/METADATA
get_stick_bugged_lmao-1.0.2.dist-info/WHEEL
get_stick_bugged_lmao-1.0.2.dist-info/entry_points.txt
get_stick_bugged_lmao-1.0.2.dist-info/top_level.txt
get_stick_bugged_lmao-1.0.2.dist-info/RECORD
