Metadata-Version: 2.1
Name: get-stick-bugged-lmao
Version: 1.0.2
Summary: 'Get stick bugged' video generator
Home-page: https://github.com/meowscatter/get-stick-bugged-lol
Author: n0spaces
Classifier: Programming Language :: Python :: 3
Classifier: License :: OSI Approved :: MIT License
Classifier: Operating System :: OS Independent
Requires-Python: >=3.6
License-File: LICENSE
Requires-Dist: Pillow
Requires-Dist: moviepy
Requires-Dist: numpy
Requires-Dist: pylsd-nova (>=1.2.0)
